README.md
setup.py
py_librus_api/__init__.py
py_librus_api/librus.py
py_librus_api.egg-info/PKG-INFO
py_librus_api.egg-info/SOURCES.txt
py_librus_api.egg-info/dependency_links.txt
py_librus_api.egg-info/top_level.txt