Metadata-Version: 2.1
Name: py-librus-api
Version: 0.3.0
Summary: A librus api made in python.
Home-page: https://github.com/TheAmazingRak/py-librus-api
Author: Tomasz Nieżurawski
Author-email: tomek.niezurawski@gmail.com
License: UNKNOWN
Platform: UNKNOWN
Classifier: Programming Language :: Python :: 3
Classifier: License :: OSI Approved :: MIT License
Classifier: Operating System :: OS Independent
